{
	"enable": true,
	"description": "<sup><abbr title=\"默认为所有用户启用\">D</abbr></sup><span id=\"Gadget-AjaxLogin\"></span> AjaxLogin <small>通过Ajax技术，直接在首页弹出登录界面，不再跳转至登录页</small>",
	"section": "browser",
	"default": true,
	"dependencies": [
		"ext.gadget.FilterAlteredClicks",
		"ext.gadget.i18n",
		"ext.gadget.React",
		"ext.gadget.Toastify",
		"ext.gadget.Util",
		"mediawiki.api",
		"mediawiki.util",
		"oojs-ui-core",
		"oojs-ui-windows",
		"oojs-ui.styles.icons-interactions",
		"oojs-ui.styles.icons-user"
	],
	"hidden": true
}
